{
  "schemaVersion": 1,
  "id": "animation",
  "version": "${version}",

  "name": "Example Mod",
  "description": "An animation API for Fabric Minecraft mods",
  "authors": [
    "kwerti"
  ],
  "contact": {
    "homepage": "https://fabricmc.net/",
    "sources": "https://github.com/FabricMC/fabric-example-mod"
  },

  "license": "MIT",
  "icon": "assets/animation/icon.png",

  "environment": "*",
  "entrypoints": {
    "main": [
      "net.fabricmc.example.ExampleMod"
    ]
  },
  "mixins": [
    "modid.mixins.json"
  ],

  "depends": {
    "fabricloader": ">=0.4.0",
    "fabric": "*"
  },
  "suggests": {
    "flamingo": "*"
  }
}
